Workbook

Sheet Executive Summary
A1: NOESIS.IO HEALTH - EXECUTIVE SUMMARY
A2: Powered by Athena Core Technologies
A4: Metric | B4: Year 1 | C4: Year 2 | D4: Year 3 | E4: Year 4 | F4: Year 5
A5: Annual Recurring Revenue (ARR) | B5: ='Revenue Model'!B20 | C5: ='Revenue Model'!C20 | D5: ='Revenue Model'!D20 | E5: ='Revenue Model'!E20 | F5: ='Revenue Model'!F20
A6: Total Customers | B6: ='Revenue Model'!B19 | C6: ='Revenue Model'!C19 | D6: ='Revenue Model'!D19 | E6: ='Revenue Model'!E19 | F6: ='Revenue Model'!F19
A7: Net Revenue Retention (%) | B7: ='Unit Economics'!B18 | C7: ='Unit Economics'!C18 | D7: ='Unit Economics'!D18 | E7: ='Unit Economics'!E18 | F7: ='Unit Economics'!F18
A8: Gross Margin (%) | B8: ='P&L'!B27 | C8: ='P&L'!C27 | D8: ='P&L'!D27 | E8: ='P&L'!E27 | F8: ='P&L'!F27
A9: EBITDA Margin (%) | B9: ='P&L'!B37 | C9: ='P&L'!C37 | D9: ='P&L'!D37 | E9: ='P&L'!E37 | F9: ='P&L'!F37
A10: Cash Position | B10: ='Cash Flow'!B18 | C10: ='Cash Flow'!C18 | D10: ='Cash Flow'!D18 | E10: ='Cash Flow'!E18 | F10: ='Cash Flow'!F18

Sheet Revenue Model
A1: REVENUE MODEL
A3: KEY ASSUMPTIONS
A4: Essentials Pricing (monthly) | B4: 499
A5: Professional Pricing (monthly) | B5: 999
A6: Enterprise Pricing (monthly) | B6: 2499
A7: Transaction Fee per Claim | B7: 0.5
A8: Professional Services per New Customer | B8: 5000
A9: Transaction Volume per Practice (monthly claims) | B9: 500
A10: Monthly Churn Rate Y1 | B10: 0.02
A11: Monthly Churn Rate Y2 | B11: 0.015
A12: Monthly Churn Rate Y3-5 | B12: 0.012
A14: PRICING TIER ANALYSIS
B15: Year 1 | C15: Year 2 | D15: Year 3 | E15: Year 4 | F15: Year 5
A16: ESSENTIALS TIER ($499/mo) | B16: 10 | C16: 35 | D16: 90 | E16: 180 | F16: 300
A17: PROFESSIONAL TIER ($999/mo) | B17: 20 | C17: 55 | D17: 140 | E17: 280 | F17: 450
A18: ENTERPRISE TIER ($2,499/mo) | B18: 10 | C18: 30 | D18: 70 | E18: 140 | F18: 250
A19: TOTAL CUSTOMERS | B19: =SUM(B16:B18) | C19: =SUM(C16:C18) | D19: =SUM(D16:D18) | E19: =SUM(E16:E18) | F19: =SUM(F16:F18)
A20: TOTAL ARR | B20: =(B16*$B$4*12)+(B17*$B$5*12)+(B18*$B$6*12) | C20: =(C16*$B$4*12)+(C17*$B$5*12)+(C18*$B$6*12) | D20: =(D16*$B$4*12)+(D17*$B$5*12)+(D18*$B$6*12) | E20: =(E16*$B$4*12)+(E17*$B$5*12)+(E18*$B$6*12) | F20: =(F16*$B$4*12)+(F17*$B$5*12)+(F18*$B$6*12)
A21: TRANSACTION REVENUE (claims) | B21: =B19*$B$10*12*$B$4 | C21: =C19*$B$10*12*$B$4 | D21: =D19*$B$10*12*$B$4 | E21: =E19*$B$10*12*$B$4 | F21: =F19*$B$10*12*$B$4
A22: PROFESSIONAL SERVICES REVENUE | B22: =10*$B$5 | C22: =25*$B$5 | D22: =55*$B$5 | E22: =190*$B$5 | F22: =120*$B$5
A23: TOTAL REVENUE | B23: =B20+B21+B22 | C23: =C20+C21+C22 | D23: =D20+D21+D22 | E23: =E20+E21+E22 | F23: =F20+F21+F22

Sheet Unit Economics
A1: UNIT ECONOMICS ANALYSIS
A3: Metric | B3: Year 1 | C3: Year 2 | D3: Year 3 | E3: Year 4 | F3: Year 5
A4: Sales & Marketing Spend | B4: ='Headcount Plan'!B11 | C4: ='Headcount Plan'!C11 | D4: ='Headcount Plan'!D11 | E4: ='Headcount Plan'!E11 | F4: ='Headcount Plan'!F11
A5: New Customers | B5: 40 | C5: 80 | D5: 180 | E5: 300 | F5: 400
A6: Customer Acquisition Cost (CAC) | B6: =B4/B5 | C6: =C4/C5 | D6: =D4/D5 | E6: =E4/E5 | F6: =F4/F5
A8: Average Revenue per Customer (ARPC) | B8: ='Revenue Model'!B23/'Revenue Model'!B19 | C8: ='Revenue Model'!C23/'Revenue Model'!C19 | D8: ='Revenue Model'!D23/'Revenue Model'!D19 | E8: ='Revenue Model'!E23/'Revenue Model'!E19 | F8: ='Revenue Model'!F23/'Revenue Model'!F19
A9: Gross Margin % | B9: ='P&L'!B27 | C9: ='P&L'!C27 | D9: ='P&L'!D27 | E9: ='P&L'!E27 | F9: ='P&L'!F27
A10: Monthly Churn Rate | B10: 0.02 | C10: 0.015 | D10: 0.012 | E10: 0.012 | F10: 0.012
A11: Lifetime Value (LTV) | B11: =(B8*B9)/B10 | C11: =(C8*C9)/C10 | D11: =(D8*D9)/D10 | E11: =(E8*E9)/E10 | F11: =(F8*F9)/F10
A12: LTV:CAC Ratio | B12: =B11/B6 | C12: =C11/C6 | D12: =D11/D6 | E12: =E11/E6 | F12: =F11/F6
A13: Payback Period (months) | B13: =B6/(B8*B9) | C13: =C6/(C8*C9) | D13: =D6/(D8*D9) | E13: =E6/(E8*E9) | F13: =F6/(F8*F9)
A15: Net Revenue Retention (NRR) | B15: 0.95 | C15: 0.97 | D15: 0.98 | E15: 0.99 | F15: 0.99

Sheet P&L (Income Statement)
A1: PROFIT & LOSS STATEMENT
B3: Year 1 | C3: Year 2 | D3: Year 3 | E3: Year 4 | F3: Year 5
A4: Revenue | B4: ='Revenue Model'!B23 | C4: ='Revenue Model'!C23 | D4: ='Revenue Model'!D23 | E4: ='Revenue Model'!E23 | F4: ='Revenue Model'!F23
A6: Cost of Revenue
A7: Cloud Infrastructure | B7: =B4*0.15 | C7: =C4*0.13 | D7: =D4*0.12 | E7: =E4*0.11 | F7: =F4*0.1
A8: Customer Support | B8: ='Headcount Plan'!B8 | C8: ='Headcount Plan'!C8 | D8: ='Headcount Plan'!D8 | E8: ='Headcount Plan'!E8 | F8: ='Headcount Plan'!F8
A9: Payment Processing (2.9%) | B9: ='Revenue Model'!B21*0.029 | C9: ='Revenue Model'!C21*0.029 | D9: ='Revenue Model'!D21*0.029 | E9: ='Revenue Model'!E21*0.029 | F9: ='Revenue Model'!F21*0.029
A10: Total Cost of Revenue | B10: =B7+B8+B9 | C10: =C7+C8+C9 | D10: =D7+D8+D9 | E10: =E7+E8+E9 | F10: =F7+F8+F9
A11: Gross Profit | B11: =B4-B10 | C11: =C4-C10 | D11: =D4-D10 | E11: =E4-E10 | F11: =F4-F10
A12: Gross Margin % | B12: =B11/B4 | C12: =C11/C4 | D12: =D11/D4 | E12: =E11/E4 | F12: =F11/F4
A14: Operating Expenses
A15: Research & Development | B15: ='Headcount Plan'!B5 | C15: ='Headcount Plan'!C5 | D15: ='Headcount Plan'!D5 | E15: ='Headcount Plan'!E5 | F15: ='Headcount Plan'!F5
A16: Sales & Marketing | B16: ='Headcount Plan'!B11 | C16: ='Headcount Plan'!C11 | D16: ='Headcount Plan'!D11 | E16: ='Headcount Plan'!E11 | F16: ='Headcount Plan'!F11
A17: General & Administrative | B17: ='Headcount Plan'!B14 | C17: ='Headcount Plan'!C14 | D17: ='Headcount Plan'!D14 | E17: ='Headcount Plan'!E14 | F17: ='Headcount Plan'!F14
A18: Total Operating Expenses | B18: =B15+B16+B17 | C18: =C15+C16+C17 | D18: =D15+D16+D17 | E18: =E15+E16+E17 | F18: =F15+F16+F17
A20: EBITDA | B20: =B11-B18 | C20: =C11-C18 | D20: =D11-D18 | E20: =E11-E18 | F20: =F11-F18
A21: EBITDA Margin % | B21: =B20/B4 | C21: =C20/C4 | D21: =D20/D4 | E21: =E20/E4 | F21: =F20/F4
A23: Depreciation & Amortization | B23: 200000 | C23: 250000 | D23: 300000 | E23: 350000 | F23: 400000
A24: Interest Expense | B24: 500000 | C24: 400000 | D24: 300000 | E24: 200000 | F24: 100000
A25: Operating Income (before tax) | B25: =B20-B23-B24 | C25: =C20-C23-C24 | D25: =D20-D23-D24 | E25: =E20-E23-E24 | F25: =F20-F23-F24
A26: Taxes (21%) | B26: =MAX(B25*0.21,0) | C26: =MAX(C25*0.21,0) | D26: =MAX(D25*0.21,0) | E26: =MAX(E25*0.21,0) | F26: =MAX(F25*0.21,0)
A27: Net Income | B27: =B25-B26 | C27: =C25-C26 | D27: =D25-D26 | E27: =E25-E26 | F27: =F25-F26

Sheet Headcount Plan
A1: HEADCOUNT PLAN & PEOPLE COSTS
A3: Department | B3: Year 1 | C3: Year 2 | D3: Year 3 | E3: Year 4 | F3: Year 5
A4: Engineering | B4: 4 | C4: 7 | D4: 12 | E4: 18 | F4: 25
A5: Product | B5: 1 | C5: 2 | D5: 3 | E5: 4 | F5: 5
A6: Sales | B6: 2 | C6: 5 | D6: 10 | E6: 15 | F6: 20
A7: Marketing | B7: 1 | C7: 2 | D7: 4 | E7: 6 | F7: 8
A8: Customer Success | B8: 2 | C8: 5 | D8: 10 | E8: 15 | F8: 20
A9: G&A | B9: 2 | C9: 3 | D9: 4 | E9: 5 | F9: 6
A10: TOTAL HEADCOUNT | B10: =SUM(B4:B9) | C10: =SUM(C4:C9) | D10: =SUM(D4:D9) | E10: =SUM(E4:E9) | F10: =SUM(F4:F9)
A12: AVERAGE SALARY BY DEPARTMENT
A13: Department | B13: Year 1 | C13: Year 2 | D13: Year 3 | E13: Year 4 | F13: Year 5
A14: Engineering | B14: 120000 | C14: 125000 | D14: 130000 | E14: 135000 | F14: 140000
A15: Product | B15: 110000 | C15: 115000 | D15: 120000 | E15: 125000 | F15: 130000
A16: Sales | B16: 90000 | C16: 95000 | D16: 100000 | E16: 105000 | F16: 110000
A17: Marketing | B17: 85000 | C17: 90000 | D17: 95000 | E17: 100000 | F17: 105000
A18: Customer Success | B18: 75000 | C18: 80000 | D18: 85000 | E18: 90000 | F18: 95000
A19: G&A | B19: 100000 | C19: 105000 | D19: 110000 | E19: 115000 | F19: 120000
A21: TOTAL PEOPLE COSTS (incl 1.3x benefits) | B21: =((B4*B14)+(B5*B15)+(B6*B16)+(B7*B17)+(B8*B18)+(B9*B19))*1.3 | C21: =((C4*C14)+(C5*C15)+(C6*C16)+(C7*C17)+(C8*C18)+(C9*C19))*1.3 | D21: =((D4*D14)+(D5*D15)+(D6*D16)+(D7*D17)+(D8*D18)+(D9*D19))*1.3 | E21: =((E4*E14)+(E5*E15)+(E6*E16)+(E7*E17)+(E8*E18)+(E9*E19))*1.3 | F21: =((F4*F14)+(F5*F15)+(F6*F16)+(F7*F17)+(F8*F18)+(F9*F19))*1.3
A23: COST BY DEPARTMENT
A24: Department | B24: Year 1 | C24: Year 2 | D24: Year 3 | E24: Year 4 | F24: Year 5
A25: Engineering | B25: =(B4*B14)*1.3 | C25: =(C4*C14)*1.3 | D25: =(D4*D14)*1.3 | E25: =(E4*E14)*1.3 | F25: =(F4*F14)*1.3
A26: Product | B26: =(B5*B15)*1.3 | C26: =(C5*C15)*1.3 | D26: =(D5*D15)*1.3 | E26: =(E5*E15)*1.3 | F26: =(F5*F15)*1.3
A27: Sales | B27: =(B6*B16)*1.3 | C27: =(C6*C16)*1.3 | D27: =(D6*D16)*1.3 | E27: =(E6*E16)*1.3 | F27: =(F6*F16)*1.3
A28: Marketing | B28: =(B7*B17)*1.3 | C28: =(C7*C17)*1.3 | D28: =(D7*D17)*1.3 | E28: =(E7*E17)*1.3 | F28: =(F7*F17)*1.3
A29: Customer Success | B29: =(B8*B18)*1.3 | C29: =(C8*C18)*1.3 | D29: =(D8*D18)*1.3 | E29: =(E8*E18)*1.3 | F29: =(F8*F18)*1.3
A30: G&A | B30: =(B9*B19)*1.3 | C30: =(C9*C19)*1.3 | D30: =(D9*D19)*1.3 | E30: =(E9*E19)*1.3 | F30: =(F9*F19)*1.3
A32: R&D COST (for P&L) | B32: =B25 | C32: =C25 | D32: =D25 | E32: =E25 | F32: =F25
A33: CUSTOMER SUCCESS COST (for COGS) | B33: =B29 | C33: =C29 | D33: =D29 | E33: =E29 | F33: =F29
A34: SALES & MARKETING COST (for OpEx) | B34: =B27 | C34: =C27 | D34: =D27 | E34: =E27 | F34: =F27
A35: G&A COST (for OpEx) | B35: =B30 | C35: =C30 | D35: =D30 | E35: =E30 | F35: =F30
A37: Revenue per Employee | B37: ='Revenue Model'!B23/B10 | C37: ='Revenue Model'!C23/C10 | D37: ='Revenue Model'!D23/D10 | E37: ='Revenue Model'!E23/E10 | F37: ='Revenue Model'!F23/F10

Sheet Cash Flow
A1: CASH FLOW STATEMENT
B3: Year 0 | C3: Year 1 | D3: Year 2 | E3: Year 3 | F3: Year 4 | G3: Year 5
A4: Beginning Cash Balance | B4: 15000000 | C4: =B18 | D4: =C18 | E4: =D18 | F4: =E18
A6: Cash Inflows
A7: Revenue (cash collected) | C7: ='Revenue Model'!C23*0.95 | D7: ='Revenue Model'!D23*0.95 | E7: ='Revenue Model'!E23*0.95 | F7: ='Revenue Model'!F23*0.95
A9: Cash Outflows
A10: Operating Expenses | C10: ='P&L'!C18 | D10: ='P&L'!D18 | E10: ='P&L'!E18 | F10: ='P&L'!F18
A11: Cost of Revenue | C11: ='P&L'!C10 | D11: ='P&L'!D10 | E11: ='P&L'!E10 | F11: ='P&L'!F10
A12: 0 | B12: 500000 | C12: 600000 | D12: 700000 | E12: 800000 | F12: 900000
A13: 0 | B13: 0 | C13: 0 | D13: 0 | E13: 0 | F13: 0
A14: Total Cash Outflows | C14: =C10+C11+C12+C13 | D14: =D10+D11+D12+D13 | E14: =E10+E11+E12+E13 | F14: =F10+F11+F12+F13
A16: Net Cash Flow | C16: =C7-C14 | D16: =D7-D14 | E16: =E7-E14 | F16: =F7-F14
A18: Ending Cash Balance | B18: 15000000 | C18: =B18+C16 | D18: =C18+D16 | E18: =D18+E16 | F18: =E18+F16
A20: Months of Runway | C20: =IF(C14>0,'Positive CF',C18/=ABS(C14/12)) | D20: =IF(D14>0,'Positive CF',D18/=ABS(D14/12)) | E20: =IF(E14>0,'Positive CF',E18/=ABS(E14/12)) | F20: =IF(F14>0,'Positive CF',F18/=ABS(F14/12))

Sheet Assumptions
A1: KEY ASSUMPTIONS & INPUTS
A3: MARKET & BUSINESS
A4: Total Addressable Market (TAM) | B4: 47000000000
A5: Serviceable Addressable Market (SAM) | B5: 5000000000
A6: Target Market Penetration Year 5 | B6: 0.02
A8: PRICING STRATEGY
A9: Essentials Tier Monthly Price | B9: 499
A10: Professional Tier Monthly Price | B10: 999
A11: Enterprise Tier Monthly Price | B11: 2499
A12: Transaction Fee per Claim | B12: 0.5
A13: Professional Services per Customer | B13: 5000
A15: CUSTOMER ACQUISITION
A16: Year 1 New Customers | B16: 40
A17: Year 2 New Customers | B17: 80
A18: Year 3 New Customers | B18: 180
A19: Year 4 New Customers | B19: 300
A20: Year 5 New Customers | B20: 400
A22: CHURN RATES (MONTHLY)
A23: Year 1 Churn Rate | B23: 0.02
A24: Year 2 Churn Rate | B24: 0.015
A25: Year 3-5 Churn Rate | B25: 0.012
A27: COST STRUCTURE
A28: Infrastructure Cost % of Revenue Y1 | B28: 0.15
A29: Infrastructure Cost % of Revenue Y5 | B29: 0.1
A30: Payment Processing Fee | B30: 0.029
A31: Benefits Multiplier | B31: 1.3
A32: Tax Rate | B32: 0.21
A34: HEADCOUNT
A35: Initial Engineering Headcount | B35: 4
A36: Year 5 Engineering Headcount | B36: 25
A37: Initial Total Company Size | B37: 12
A38: Year 5 Total Company Size | B38: 58
